<news>
<date>Październik 23, 2009</date>
<title>Wydano Wine 1.1.32</title>
<body>
<p> Wydanie rozwojowe Wine 1.1.32 jest już dostępne.</p>
<p> <a href="{$root}/announce/1.1.32">Co nowego</a> w tym wydaniu:
<ul>
  <li>Wiele poprawek crypto, szczególnie na 64-bitach.</li>
  <li>Ulepszono dostęp do DVD na Mac OS.</li>
  <li>Kilka ulepszeń w powszechnych kontrolkach (ang. common controls).</li>
  <li>Rozmaite ulepszenia we wsparciu HTML.</li>
  <li>Więcej optymalizacji DIB.</li>
  <li>Rozmaite poprawki błędów.</li>
</ul></p>
<p><p>Źródło jest <a href="http://prdownloads.sourceforge.net/wine/wine-1.1.32.tar.bz2">już dostępne</a>.
Paczki binarne są w trakcie budowy i ukażą się wkróce w przeznaczonych dla nich <a href="{$root}/download">pobieralniach</a>.
</p></body></news>
